healthpy/__init__.py
healthpy/_http.py
healthpy/_response.py
healthpy/_status.py
healthpy/flask_restx.py
healthpy/http.py
healthpy/httpx.py
healthpy/redis.py
healthpy/requests.py
healthpy/starlette.py
healthpy/testing.py
healthpy/version.py
healthpy-1.14.0.dist-info/LICENSE
healthpy-1.14.0.dist-info/METADATA
healthpy-1.14.0.dist-info/WHEEL
healthpy-1.14.0.dist-info/top_level.txt
healthpy-1.14.0.dist-info/RECORD
