Metadata-Version: 2.1
Name: healthpy
Version: 1.14.0
Summary: Health Check for HTTP APIs
Home-page: https://colin-b.github.io/healthpy/
Author: Colin Bounouar
Author-email: colin.bounouar.dev@gmail.com
Maintainer: Colin Bounouar
Maintainer-email: colin.bounouar.dev@gmail.com
License: MIT
Download-URL: https://pypi.org/project/healthpy/
Project-URL: GitHub, https://github.com/Colin-b/healthpy
Project-URL: Changelog, https://github.com/Colin-b/healthpy/blob/master/CHANGELOG.md
Project-URL: Issues, https://github.com/Colin-b/healthpy/issues
Keywords: health,api,http,redis
Platform: Windows
Platform: Linux
Classifier: Development Status :: 5 - Production/Stable
Classifier: Intended Audience :: Developers
Classifier: License :: OSI Approved :: MIT License
Classifier: Natural Language :: English
Classifier: Programming Language :: Python
Classifier: Programming Language :: Python :: 3
Classifier: Programming Language :: Python :: 3.7
Classifier: Programming Language :: Python :: 3.8
Classifier: Programming Language :: Python :: 3.9
Classifier: Topic :: Software Development :: Build Tools
Requires-Python: >=3.7
Provides-Extra: testing
Requires-Dist: pytest-responses (==0.4.*) ; extra == 'testing'
Requires-Dist: pytest-httpx (==0.10.*) ; extra == 'testing'
Requires-Dist: redis (==3.*) ; extra == 'testing'
Requires-Dist: starlette (==0.13.*) ; extra == 'testing'
Requires-Dist: flask-restx (==0.2.*) ; extra == 'testing'
Requires-Dist: pytest-cov (==2.*) ; extra == 'testing'
